imcascade/__init__.py
imcascade/fitter.py
imcascade/mgm.py
imcascade/psf_fitter.py
imcascade/results.py
imcascade/utils.py
imcascade-1.1.dist-info/LICENSE
imcascade-1.1.dist-info/METADATA
imcascade-1.1.dist-info/WHEEL
imcascade-1.1.dist-info/top_level.txt
imcascade-1.1.dist-info/RECORD
