Metadata-Version: 2.1
Name: imcascade
Version: 1.1
Summary: imcascade: Fitting astronomical images using a 'cascade' of Gaussians
Home-page: https://github.com/tbmiller-astro/imcascade
Author: Tim Miller
Author-email: tim.miller@yale.edu
License: MIT
Classifier: Development Status :: 4 - Beta
Classifier: Intended Audience :: Science/Research
Classifier: License :: OSI Approved :: MIT License
Classifier: Operating System :: OS Independent
Classifier: Programming Language :: Python :: 3.5
Classifier: Programming Language :: Python :: 3.6
Classifier: Programming Language :: Python :: 3.7
Classifier: Topic :: Scientific/Engineering :: Astronomy
Classifier: Topic :: Scientific/Engineering :: Physics
License-File: LICENSE
Requires-Dist: numpy
Requires-Dist: scipy
Requires-Dist: asdf
Requires-Dist: dynesty
Requires-Dist: numba
Requires-Dist: astropy
Requires-Dist: sep
